sym_lambda-1.0.0b1-py3.8-nspkg.pth
sym/lambda/__init__.py
sym/lambda/util.py
sym_lambda-1.0.0b1.dist-info/METADATA
sym_lambda-1.0.0b1.dist-info/WHEEL
sym_lambda-1.0.0b1.dist-info/namespace_packages.txt
sym_lambda-1.0.0b1.dist-info/top_level.txt
sym_lambda-1.0.0b1.dist-info/RECORD
